http_request/__init__.py
http_request/http_request.py
backwork_notifier_http_new-0.1.0.dist-info/LICENSE
backwork_notifier_http_new-0.1.0.dist-info/METADATA
backwork_notifier_http_new-0.1.0.dist-info/WHEEL
backwork_notifier_http_new-0.1.0.dist-info/entry_points.txt
backwork_notifier_http_new-0.1.0.dist-info/top_level.txt
backwork_notifier_http_new-0.1.0.dist-info/RECORD
